odoo/addons/fetchmail_mail_activity_team_activity/README.rst
odoo/addons/fetchmail_mail_activity_team_activity/__init__.py
odoo/addons/fetchmail_mail_activity_team_activity/__manifest__.py
odoo/addons/fetchmail_mail_activity_team_activity/i18n/fetchmail_mail_activity_team_activity.pot
odoo/addons/fetchmail_mail_activity_team_activity/models/__init__.py
odoo/addons/fetchmail_mail_activity_team_activity/models/mail_thread.py
odoo/addons/fetchmail_mail_activity_team_activity/static/description/icon.png
odoo/addons/fetchmail_mail_activity_team_activity/tests/__init__.py
odoo/addons/fetchmail_mail_activity_team_activity/tests/test_activity.py
odoo_addon_fetchmail_mail_activity_team_activity-15.0.1.0.0.3.dist-info/METADATA
odoo_addon_fetchmail_mail_activity_team_activity-15.0.1.0.0.3.dist-info/WHEEL
odoo_addon_fetchmail_mail_activity_team_activity-15.0.1.0.0.3.dist-info/top_level.txt
odoo_addon_fetchmail_mail_activity_team_activity-15.0.1.0.0.3.dist-info/RECORD
