Metadata-Version: 2.1
Name: odoo-addon-fetchmail-mail-activity-team-activity
Version: 15.0.1.0.0.3
Summary: * Uses mail.activity.team to configure automatic activities when mails arrive for the specified models. * The configuration to add RMA and PO models (Settings --> Technical --> Activity Teams menu)
Home-page: https://github.com/OCA/social
Author: initOS GmbH, Odoo Community Association (OCA)
Author-email: support@odoo-community.org
License: AGPL-3
Platform: UNKNOWN
Classifier: Programming Language :: Python
Classifier: Framework :: Odoo
Classifier: Framework :: Odoo :: 15.0
Classifier: License :: OSI Approved :: GNU Affero General Public License v3
Classifier: Development Status :: 3 - Alpha
Requires-Python: >=3.8
Requires-Dist: odoo-addon-mail-activity-team (<15.1dev,>=15.0dev)
Requires-Dist: odoo (<15.1dev,>=15.0a)
